codesynth/__init__.py
codesynth/ast.py
codesynth/lib.py
codesynth-0.1.0.dist-info/METADATA
codesynth-0.1.0.dist-info/WHEEL
codesynth-0.1.0.dist-info/RECORD
